pygrouper/__init__.py
pygrouper/core.py
pygrouper/models.py
pygrouper-1.0.4.dist-info/LICENSE
pygrouper-1.0.4.dist-info/METADATA
pygrouper-1.0.4.dist-info/WHEEL
pygrouper-1.0.4.dist-info/top_level.txt
pygrouper-1.0.4.dist-info/RECORD
