Metadata-Version: 2.1
Name: pygrouper
Version: 1.0.4
Summary: simple realisation of cross-reference grouping algorithm; mostly used in event driven distributed systems
Home-page: https://github.com/bl17zar/pygrouper
Author: bl17zar
Author-email: bl17zar@gmail.com
License: UNKNOWN
Platform: UNKNOWN
Classifier: Programming Language :: Python :: 3
Classifier: License :: OSI Approved :: MIT License
Classifier: Operating System :: OS Independent
Requires-Python: >=3.6
